{"version":{"pluginId":"contributor","version":"current","label":"Next","banner":null,"badge":false,"noIndex":false,"className":"docs-version-current","isLast":true,"docsSidebars":{"contributorSidebar":[{"type":"link","href":"/contributor/","label":"Overview","docId":"overview","unlisted":false},{"type":"category","label":"Development","collapsible":false,"items":[{"type":"link","href":"/contributor/development/project-structure","label":"Project structure","docId":"development/project-structure","unlisted":false},{"type":"link","href":"/contributor/development/scripts","label":"Scripts Overview","docId":"development/scripts","unlisted":false},{"type":"link","href":"/contributor/development/versioning","label":"Version history","docId":"development/versioning","unlisted":false},{"type":"link","href":"/contributor/development/visual-tests","label":"Visual regression tests","docId":"development/visual-tests","unlisted":false}],"collapsed":false},{"type":"category","label":"Release Pipeline","items":[{"type":"link","href":"/contributor/deployment/github-actions","label":"Deployments","docId":"deployment/github-actions","unlisted":false},{"type":"link","href":"/contributor/deployment/npm-publishing","label":"Releases","docId":"deployment/npm-publishing","unlisted":false}],"collapsed":true,"collapsible":true}]},"docs":{"deployment/github-actions":{"id":"deployment/github-actions","title":"Deployments","description":"Deployments are fully automatic on merge to main; production promotion is one manual click.","sidebar":"contributorSidebar"},"deployment/npm-publishing":{"id":"deployment/npm-publishing","title":"Releases","description":"Three independently versioned artifacts, each with its own release workflow:","sidebar":"contributorSidebar"},"development/project-structure":{"id":"development/project-structure","title":"Project structure","description":"Apollon is a pnpm-workspaces monorepo. Top-level layout:","sidebar":"contributorSidebar"},"development/scripts":{"id":"development/scripts","title":"Scripts Overview","description":"Here are the commonly used scripts defined in the monorepo:","sidebar":"contributorSidebar"},"development/versioning":{"id":"development/versioning","title":"Version history","description":"Apollon Standalone gives every diagram a Figma-shaped version history:","sidebar":"contributorSidebar"},"development/visual-tests":{"id":"development/visual-tests","title":"Visual regression tests","description":"Apollon's visual regression tests run as part of pr-health-checks.yml on every PR. They use Playwright with the mcr.microsoft.com/playwright:v1.59.1-noble Docker image so snapshots are pinned to one Linux rendering stack regardless of contributor OS.","sidebar":"contributorSidebar"},"overview":{"id":"overview","title":"Overview","description":"Working in the Apollon monorepo — pnpm + Node 24 + Vite.","sidebar":"contributorSidebar"}}}}